./.gitignore
./LICENSE
./PKG-INFO
./README.md
./cli.py
./comparesv.py
./pyproject.toml
./tests.py
./uv.lock
./version.py
./.claude/settings.local.json
comparesv-0.17.dist-info/METADATA
comparesv-0.17.dist-info/WHEEL
comparesv-0.17.dist-info/entry_points.txt
comparesv-0.17.dist-info/licenses/LICENSE
comparesv-0.17.dist-info/RECORD
