Metadata-Version: 2.4
Name: comparesv
Version: 0.17
Summary: CSV Comparison on steroids
Project-URL: Homepage, https://github.com/kishorek/comparesv
Project-URL: Repository, https://github.com/kishorek/comparesv
Project-URL: Issues, https://github.com/kishorek/comparesv/issues
Author-email: Kishore Kumar <ukisho@gmail.com>
License-Expression: MIT
License-File: LICENSE
Keywords: Analysis,CSV,Compare,Comparison,Data
Classifier: Development Status :: 4 - Beta
Classifier: Intended Audience :: Developers
Classifier: Intended Audience :: End Users/Desktop
Classifier: License :: OSI Approved :: MIT License
Classifier: Natural Language :: English
Classifier: Operating System :: OS Independent
Classifier: Programming Language :: Python :: 3
Classifier: Programming Language :: Python :: 3.8
Classifier: Programming Language :: Python :: 3.9
Classifier: Programming Language :: Python :: 3.10
Classifier: Programming Language :: Python :: 3.11
Classifier: Programming Language :: Python :: 3.12
Classifier: Topic :: Scientific/Engineering :: Information Analysis
Classifier: Topic :: Software Development :: Libraries :: Python Modules
Classifier: Topic :: Utilities
Requires-Python: >=3.8
Requires-Dist: chardet>=5.2.0
Requires-Dist: doublemetaphone>=0.1
Requires-Dist: rapidfuzz>=3.6.0
Requires-Dist: tqdm>=4.66.0
Requires-Dist: unidecode>=1.3.8
